cli/__init__.py
cli/common.py
cli/compiler.py
cli/constant.py
cli/debug_bridge.py
cli/ext_rule_checker.py
cli/main.py
cli/reverse_compile.py
cli/xml2tree.py
cli/res/__init__.py
cli/res/debug_info.html.jinja2
dmb_cli-3.1.10.dist-info/LICENSE
dmb_cli-3.1.10.dist-info/METADATA
dmb_cli-3.1.10.dist-info/WHEEL
dmb_cli-3.1.10.dist-info/entry_points.txt
dmb_cli-3.1.10.dist-info/top_level.txt
dmb_cli-3.1.10.dist-info/RECORD
