Metadata-Version: 2.1
Name: dmb-cli
Version: 3.1.10
Summary: CLI for DreamBox
Home-page: https://github.com/didi/DreamBox/tree/master/cli
Author: Kevin Liu
Author-email: airk908@gmail.com
License: UNKNOWN
Platform: UNKNOWN
Classifier: Programming Language :: Python :: 3
Classifier: License :: OSI Approved :: Apache Software License
Classifier: Operating System :: OS Independent
Requires-Python: >=3.6
Requires-Dist: lxml
Requires-Dist: watchdog
Requires-Dist: websockets
Requires-Dist: jinja2
Requires-Dist: qrcode
Requires-Dist: importlib-resources
Requires-Dist: netifaces
Requires-Dist: PyYAML
